dar_etl/__init__.py
dar_etl/config.py
dar_etl/consumer.py
dar_etl/main.py
dar_etl/publisher.py
dar_etl/version.py
dar_etl/parsing/__init__.py
dar_etl/parsing/parser.py
dar_etl/schemas/__init__.py
dar_etl/schemas/address.py
dar_etl/schemas/address_point.py
dar_etl/schemas/base_model.py
dar_etl/schemas/house_number.py
dar_etl/schemas/named_road.py
dar_etl/schemas/named_road_municipal_district.py
dar_etl/schemas/named_road_postal_code.py
dar_etl/schemas/named_road_supplementary_city_name.py
dar_etl/schemas/postal_code.py
dar_etl/schemas/root_keys.py
dar_etl/schemas/supplementary_city_name.py
dar_etl-0.1.0.dist-info/LICENSE
dar_etl-0.1.0.dist-info/METADATA
dar_etl-0.1.0.dist-info/WHEEL
dar_etl-0.1.0.dist-info/entry_points.txt
dar_etl-0.1.0.dist-info/top_level.txt
dar_etl-0.1.0.dist-info/RECORD
